{
    "uid": 100049765,
    "migrosId": "103580300000",
    "name": "Aceto Balsamico Giovane",
    "title": "Aceto Balsamico Giovane",
    "productRange": "STANDARD",
    "productAvailability": "INSTORE_ONLY",
    "productInformation": {
        "mainInformation": {
            "labels": [
                {
                    "id": "L88",
                    "name": "Nostrani del Ticino",
                    "slug": "nostrani-del-ticino",
                    "imagePath": "https://www-leshop-ch-cld-res.cloudinary.com/image/upload/{stack}/v1707838713/labels/Nostrani_del_Ticino"
                }
            ],
            "ingredients": "Balsamessig ^. \n^ aus dem Tessin (CH)",
            "allergenIndication": "Kann enthalten: Schwefeldioxid oder Sulfite.",
            "origin": "You can find information about the origin on the packaging in the store.",
            "mcheck": {
                "carbonFootprint": {
                    "rating": 5,
                    "co2CarKmEquivalent": 3,
                    "productionRatio": 66,
                    "transportRatio": 9,
                    "packagingRatio": 25,
                    "image": "https://image.migros.ch/original/3cb33aa7d90d7331f458860ae78688a0923b5993.svg",
                    "stackImage": "https://image.migros.ch/{stack}/3cb33aa7d90d7331f458860ae78688a0923b5993.svg",
                    "co2KgRange": "0 - 0.9 kg CO₂eq / kg"
                }
            },
            "rating": {
                "nbReviews": 7,
                "nbStars": 5.0
            },
            "migipediaUrl": "https://migipedia.migros.ch/de/products/103580300000"
        },
        "otherInformation": {
            "articleNumber": "103580300000",
            "legalDesignation": "Balsamessig",
            "distributorName": "Cooperativa Migros Ticino",
            "distributorStreetAndNumber": "CH-6592 S. Antonino",
            "remarks": [
                {
                    "code": "Cooling information/storage information",
                    "value": "Store in a dry place. Keep away from heat."
                }
            ],
            "mainSpecificities": [
                {
                    "code": "Packaging type",
                    "value": "Bottle"
                },
                {
                    "code": "Acid content",
                    "value": "6 %"
                },
                {
                    "code": "Production process",
                    "value": "Aus der Region"
                },
                {
                    "code": "Notes for preparation",
                    "value": "zum würzen geeignet"
                },
                {
                    "code": "Production method of vinegar",
                    "value": "Im Eichenfass gereift"
                }
            ]
        }
    },
    "gtins": [
        "7613106032085"
    ],
    "images": [
        {
            "cdn": "rokka",
            "url": "https://image.migros.ch/{stack}/d1377c45a2d3d7a9d6ed255328066b26f5e31ad2/aceto-balsamico-giovane.jpg"
        }
    ],
    "breadcrumb": [
        {
            "id": "7494735",
            "name": "Pasta, condiments & canned food",
            "slugs": [
                "pasta-condiments-canned-food"
            ]
        },
        {
            "id": "7494776",
            "name": "Spices & sauces",
            "slugs": [
                "pasta-condiments-canned-food",
                "spices-sauces"
            ]
        },
        {
            "id": "7494982",
            "name": "Oil & vinegar",
            "slugs": [
                "pasta-condiments-canned-food",
                "spices-sauces",
                "oil-vinegar"
            ]
        }
    ],
    "productUrls": "https://www.migros.ch/en/product/103580300000",
    "isMgbCompatible": true,
    "isConsignmentProduct": false,
    "offer": {
        "price": {
            "displayUnitPrice": true,
            "formattedPrice": "11.–",
            "advertisedDisplayValue": "11.–",
            "effectiveDisplayValue": "11.–",
            "multiplier": 1,
            "value": 11,
            "effectiveValue": 11,
            "advertisedValue": 11,
            "unitPrice": {
                "value": 5.5,
                "unit": "100ml"
            }
        },
        "quantity": "200ml",
        "quantityPrice": "5.50/100ml",
        "isVariableWeight": false,
        "channel": {
            "offerType": "OFFLINE",
            "region": "national"
        },
        "maxOrderableQuantityV2": 96,
        "isNewOffer": false,
        "displayPrice": true,
        "type": "STANDARD"
    },
    "dateAdded": "2024-09-16T14:30:04"
}