{
    "uid": 100004595,
    "migrosId": "519615100000",
    "migrosOnlineId": "4504402",
    "name": "Mascara",
    "brand": "L'Oréal Paris",
    "brandLine": "Lash Paradise",
    "versioning": "Black waterproof",
    "title": "L'Oréal Paris Lash Paradise · Mascara · Black waterproof",
    "description": "L'Oréal Paris Mascara Black waterproof",
    "productRange": "STANDARD",
    "productAvailability": "ONLINE_AND_INSTORE",
    "productInformation": {
        "mainInformation": {
            "brand": {
                "name": "L'Oréal Paris",
                "slug": "loreal-paris",
                "imagePath": "https://www-leshop-ch-cld-res.cloudinary.com/image/upload/{stack}/v1640076902/brands/Loreal_Paris_L_Ore%DD%81al_Suisse_SA_Logo"
            },
            "rating": {
                "nbReviews": 5,
                "nbStars": 4.0
            },
            "migipediaUrl": "https://migipedia.migros.ch/de/products/519615100000"
        },
        "usageInformation": {
            "additionalInformation": "The waterproof Paradise Extatic Mascara provides intense volume and spectacular length- Soothing, creamy formula with precious castor oil- Gently curved, ultra-soft nylon brush for comfortable application- No clumping"
        },
        "otherInformation": {
            "articleNumber": "519615100000",
            "distributorName": "Migros-Genossenschafts-Bund",
            "distributorStreetAndNumber": "Limmatstrasse 152, CH-8031 Zürich"
        }
    },
    "gtins": [
        "3600523902989",
        "3600523591831"
    ],
    "images": [
        {
            "cdn": "rokka",
            "url": "https://image.migros.ch/d/{stack}/o-af-1-t.clr-fff/0a3bb5b6f51b623db8ecb82dd686d4617c5daec1/paradise-extatic-mascara-waterproof-black.jpg"
        },
        {
            "cdn": "rokka",
            "url": "https://image.migros.ch/d/{stack}/4fd7160a905204641fbbeeb7974fe9c9b72ea894.jpg"
        }
    ],
    "breadcrumb": [
        {
            "id": "7494743",
            "name": "Drugstore & cosmetics",
            "slugs": [
                "drugstore-cosmetics"
            ]
        },
        {
            "id": "7494828",
            "name": "Facial care",
            "slugs": [
                "drugstore-cosmetics",
                "facial-care"
            ]
        },
        {
            "id": "7495247",
            "name": "Make-up",
            "slugs": [
                "drugstore-cosmetics",
                "facial-care",
                "make-up"
            ]
        }
    ],
    "productUrls": "https://www.migros.ch/en/product/519615100000",
    "isMgbCompatible": true,
    "isConsignmentProduct": false,
    "offer": {
        "price": {
            "displayUnitPrice": false,
            "formattedPrice": "24.95",
            "advertisedDisplayValue": "24.95",
            "effectiveDisplayValue": "24.95",
            "multiplier": 1,
            "value": 24.95,
            "effectiveValue": 24.95,
            "advertisedValue": 24.95
        },
        "isVariableWeight": false,
        "channel": {
            "offerType": "OFFLINE",
            "region": "national"
        },
        "maxOrderableQuantityV2": 96,
        "isNewOffer": false,
        "displayPrice": true,
        "type": "STANDARD"
    },
    "dateAdded": "2024-09-16T16:54:28"
}