{
    "uid": 100172991,
    "migrosId": "724367700000",
    "name": "3-tone cylinder candles, 7cm diameter, 2-pack, assorted",
    "brand": "MIGROS HOME",
    "title": "3-tone cylinder candles, 7cm diameter, 2-pack, assorted",
    "productRange": "STANDARD",
    "productAvailability": "INSTORE_ONLY",
    "productInformation": {
        "mainInformation": {
            "brand": {
                "name": "MIGROS HOME",
                "slug": "migros-home",
                "imagePath": "https://www-leshop-ch-cld-res.cloudinary.com/image/upload/{stack}/v1715075047/brands/MIGROS_Home_GR7"
            },
            "origin": "You can find information about the origin on the packaging in the store.",
            "migipediaUrl": "https://migipedia.migros.ch/de/products/724367700000"
        },
        "otherInformation": {
            "articleNumber": "724367700000",
            "distributorName": "Migros-Genossenschafts-Bund",
            "distributorStreetAndNumber": "Limmatstrasse 152, CH-8031 Zürich",
            "mainSpecificities": [
                {
                    "code": "Height",
                    "value": "12 cm"
                }
            ]
        }
    },
    "gtins": [
        "7628871894653"
    ],
    "images": [
        {
            "cdn": "rokka",
            "url": "https://image.migros.ch/{stack}/d15f9f3437a6782c650937867566e42aff6394f9/3-tone-cylinder-candles-7cm-diameter-2-pack-assorted.jpg"
        },
        {
            "cdn": "rokka",
            "url": "https://image.migros.ch/{stack}/588b79219a867517f0fe9c652420e72a86d26941.jpg"
        },
        {
            "cdn": "rokka",
            "url": "https://image.migros.ch/{stack}/d627edf518e4c6d07fc849efa52a2292c9910cbd.jpg"
        }
    ],
    "breadcrumb": [
        {
            "id": "7494741",
            "name": "Household and living",
            "slugs": [
                "household-and-living"
            ]
        },
        {
            "id": "7494811",
            "name": "Household aids",
            "slugs": [
                "household-and-living",
                "household-aids"
            ]
        },
        {
            "id": "7495616",
            "name": "Candles and candlesticks",
            "slugs": [
                "household-and-living",
                "household-aids",
                "candles-and-candlesticks"
            ]
        }
    ],
    "productUrls": "https://www.migros.ch/en/product/724367700000",
    "isMgbCompatible": true,
    "isConsignmentProduct": false,
    "offer": {
        "price": {
            "displayUnitPrice": false,
            "formattedPrice": "6.95",
            "advertisedDisplayValue": "6.95",
            "effectiveDisplayValue": "6.95",
            "multiplier": 1,
            "value": 6.95,
            "effectiveValue": 6.95,
            "advertisedValue": 6.95
        },
        "quantity": "1 piece",
        "isVariableWeight": false,
        "channel": {
            "offerType": "OFFLINE",
            "region": "national"
        },
        "maxOrderableQuantityV2": 96,
        "isNewOffer": false,
        "displayPrice": true,
        "type": "STANDARD"
    },
    "dateAdded": "2024-09-17T08:04:49"
}