{
    "uid": 100057079,
    "migrosId": "747513500000",
    "name": "TONIES KASPERLI (MUNDART) - ZOO / PIRAT",
    "brand": "tonies®",
    "title": "TONIES KASPERLI (MUNDART) - ZOO / PIRAT",
    "productRange": "STANDARD",
    "productAvailability": "INSTORE_ONLY",
    "productInformation": {
        "mainInformation": {
            "brand": {
                "name": "tonies®",
                "slug": "tonies",
                "imagePath": "https://www-leshop-ch-cld-res.cloudinary.com/image/upload/{stack}/v1640077204/brands/Tonies_Toymania_GmbH_Logo"
            },
            "origin": "You can find information about the origin on the packaging in the store.",
            "rating": {
                "nbReviews": 8,
                "nbStars": 5.0
            },
            "migipediaUrl": "https://migipedia.migros.ch/de/products/747513500000"
        },
        "otherInformation": {
            "articleNumber": "747513500000",
            "distributorName": "Migros-Genossenschafts-Bund",
            "distributorStreetAndNumber": "Limmatstrasse 152, CH-8031 Zürich"
        }
    },
    "gtins": [
        "4251192113375"
    ],
    "images": [
        {
            "cdn": "rokka",
            "url": "https://image.migros.ch/{stack}/22ec6cf470a5193f28aecc40f20bd4645acf6edb/tonies-kasperli-mundart-zoo-pirat.jpg"
        },
        {
            "cdn": "rokka",
            "url": "https://image.migros.ch/{stack}/592402fa201838e97947bd6dbfb7aada1f8141cb.jpg"
        },
        {
            "cdn": "rokka",
            "url": "https://image.migros.ch/{stack}/7141fc2dc88d6345edccd39b9f9b851806ed78e0.jpg"
        },
        {
            "cdn": "rokka",
            "url": "https://image.migros.ch/{stack}/8567d5ee1061915ea07f230385c675b695da4ca0.jpg"
        },
        {
            "cdn": "rokka",
            "url": "https://image.migros.ch/{stack}/2cd298b41eafd1187b2f9c8bb8ebe337fa3d689b.jpg"
        }
    ],
    "breadcrumb": [
        {
            "id": "7494742",
            "name": "Baby & kids",
            "slugs": [
                "baby-kids"
            ]
        },
        {
            "id": "7494822",
            "name": "Toys",
            "slugs": [
                "baby-kids",
                "toys"
            ]
        },
        {
            "id": "7495212",
            "name": "Games for infants",
            "slugs": [
                "baby-kids",
                "toys",
                "games-for-infants"
            ]
        }
    ],
    "productUrls": "https://www.migros.ch/en/product/747513500000",
    "isMgbCompatible": true,
    "isConsignmentProduct": false,
    "offer": {
        "price": {
            "displayUnitPrice": true,
            "formattedPrice": "19.95",
            "advertisedDisplayValue": "19.95",
            "effectiveDisplayValue": "19.95",
            "multiplier": 1,
            "value": 19.95,
            "effectiveValue": 19.95,
            "advertisedValue": 19.95,
            "unitPrice": {
                "value": 19.95,
                "unit": "piece"
            }
        },
        "quantity": "1 Stk.",
        "quantityPrice": "19.95/piece",
        "isVariableWeight": false,
        "channel": {
            "offerType": "OFFLINE",
            "region": "national"
        },
        "maxOrderableQuantityV2": 96,
        "isNewOffer": false,
        "displayPrice": true,
        "type": "STANDARD"
    },
    "dateAdded": "2024-09-16T19:33:20"
}