{
    "uid": 100129232,
    "migrosId": "196040900400",
    "name": "Genfer Eier Freiland 63g+ IP-SUISSE",
    "title": "Genfer Eier Freiland 63g+ IP-SUISSE",
    "productRange": "STANDARD",
    "productAvailability": "INSTORE_ONLY",
    "productInformation": {
        "mainInformation": {
            "labels": [
                {
                    "id": "L53",
                    "name": "Swissness",
                    "slug": "swissness",
                    "imagePath": "https://www-leshop-ch-cld-res.cloudinary.com/image/upload/{stack}/v1679483312/labels/Swissness_-_RGB_-_DEpng"
                },
                {
                    "id": "L28",
                    "name": "Aus der Region. Für die Region.",
                    "slug": "aus-der-region-fuer-die-region",
                    "imagePath": "https://www-leshop-ch-cld-res.cloudinary.com/image/upload/{stack}/v1679483580/labels/ADR_-_RGB_-_EN"
                },
                {
                    "id": "L03",
                    "name": "IP-SUISSE",
                    "slug": "ip-suisse",
                    "imagePath": "https://www-leshop-ch-cld-res.cloudinary.com/image/upload/{stack}/v1679483396/labels/IP-Suisse_-_RGB_-_DE"
                }
            ],
            "mcheck": {
                "animalWelfare": {
                    "rating": 4,
                    "image": "https://image.migros.ch/original/58bd3042b45c82e79d3a18e05d0b73cc1abda5fb.svg",
                    "label": "Animal welfare"
                }
            },
            "rating": {
                "nbReviews": 19,
                "nbStars": 4.5
            },
            "migipediaUrl": "https://migipedia.migros.ch/de/products/196040900400"
        },
        "otherInformation": {
            "articleNumber": "196040900400",
            "distributorName": "Migros-Genossenschafts-Bund",
            "distributorStreetAndNumber": "Limmatstrasse 152, CH-8031 Zürich",
            "mainSpecificities": [
                {
                    "code": "Packaging type",
                    "value": "Kartondose"
                },
                {
                    "code": "Poultry type",
                    "value": "Huhn"
                },
                {
                    "code": "Production method",
                    "value": "Freilandhaltung"
                },
                {
                    "code": "Quality of eggs",
                    "value": "roh"
                },
                {
                    "code": "Weight class of eggs",
                    "value": "63g+"
                }
            ]
        }
    },
    "gtins": [
        "7613404764213"
    ],
    "images": [
        {
            "cdn": "rokka",
            "url": "https://image.migros.ch/{stack}/8050a6165f30ce60ec7283c8c17723ef9f1acc8b/genfer-eier-freiland-63g-ip-suisse.jpg"
        }
    ],
    "breadcrumb": [
        {
            "id": "7494731",
            "name": "Dairy, eggs & fresh convenience food",
            "slugs": [
                "dairy-eggs-fresh-convenience-foo"
            ]
        },
        {
            "id": "7494751",
            "name": "Milk, butter & eggs",
            "slugs": [
                "dairy-eggs-fresh-convenience-foo",
                "milk-butter-eggs"
            ]
        },
        {
            "id": "7494870",
            "name": "Eggs",
            "slugs": [
                "dairy-eggs-fresh-convenience-foo",
                "milk-butter-eggs",
                "eggs"
            ]
        }
    ],
    "productUrls": "https://www.migros.ch/en/product/196040900400",
    "isMgbCompatible": true,
    "isConsignmentProduct": false,
    "offer": {
        "price": {
            "displayUnitPrice": true,
            "formattedPrice": "3.50",
            "advertisedDisplayValue": "3.50",
            "effectiveDisplayValue": "3.50",
            "multiplier": 1,
            "value": 3.5,
            "effectiveValue": 3.5,
            "advertisedValue": 3.5,
            "unitPrice": {
                "value": 0.88,
                "unit": "piece"
            }
        },
        "quantity": "4 Stück",
        "quantityPrice": "0.88/piece",
        "isVariableWeight": false,
        "channel": {
            "offerType": "OFFLINE",
            "region": "national"
        },
        "maxOrderableQuantityV2": 96,
        "isNewOffer": false,
        "displayPrice": true,
        "type": "STANDARD"
    },
    "dateAdded": "2024-09-16T12:08:12"
}