{
    "uid": 100068490,
    "migrosId": "514198100000",
    "migrosOnlineId": "7439825",
    "name": "Toothpaste",
    "brand": "Meridol",
    "versioning": "Soft whiteness",
    "title": "Meridol · Toothpaste · Soft whiteness",
    "description": "Meridol Toothpaste Soft whiteness",
    "productRange": "STANDARD",
    "productAvailability": "ONLINE_AND_INSTORE",
    "productInformation": {
        "mainInformation": {
            "brand": {
                "name": "Meridol",
                "slug": "meridol",
                "imagePath": "https://www-leshop-ch-cld-res.cloudinary.com/image/upload/{stack}/v1652252459/brands/meridol"
            },
            "rating": {
                "nbReviews": 11,
                "nbStars": 4.5
            }
        },
        "usageInformation": {
            "additionalInformation": "meridol gentle white toothpaste fights the cause of gum inflammation - not only the symptoms. The dental care formula works effectively and gently like a balm, keeping the gums healthy. The natural whiteness of the teeth is preserved and tooth discoloration is removed. Protects against: gum inflammation, bleeding gums, receding gums, periodontitis, plaque formation & cavities, tooth discoloration."
        },
        "otherInformation": {
            "articleNumber": "514198100000",
            "distributorName": "Migros-Genossenschafts-Bund",
            "distributorStreetAndNumber": "Limmatstrasse 152, CH-8031 Zürich"
        }
    },
    "gtins": [
        "8718951535992"
    ],
    "images": [
        {
            "cdn": "rokka",
            "url": "https://image.migros.ch/d/{stack}/o-af-1-t.clr-fff/299e2c063420c1127651d90bd2474ff923acb7d0/meridol-san-weiss-zp-duo.jpg"
        }
    ],
    "breadcrumb": [
        {
            "id": "7494743",
            "name": "Drugstore & cosmetics",
            "slugs": [
                "drugstore-cosmetics"
            ]
        },
        {
            "id": "7494829",
            "name": "Dental care",
            "slugs": [
                "drugstore-cosmetics",
                "dental-care"
            ]
        },
        {
            "id": "7495250",
            "name": "Toothpaste",
            "slugs": [
                "drugstore-cosmetics",
                "dental-care",
                "toothpaste"
            ]
        }
    ],
    "productUrls": "https://www.migros.ch/en/product/514198100000",
    "isMgbCompatible": false,
    "isConsignmentProduct": false,
    "offer": {
        "isVariableWeight": false,
        "maxOrderableQuantityV2": 96,
        "isNewOffer": false,
        "displayPrice": true
    },
    "dateAdded": "2024-09-22T02:32:40"
}