{
    "uid": 100152356,
    "migrosId": "514672400000",
    "name": "NIVEA MEN SENSITIVE PO.SH",
    "brand": "Nivea",
    "title": "NIVEA MEN SENSITIVE PO.SH",
    "productRange": "STANDARD",
    "productAvailability": "INSTORE_ONLY",
    "productInformation": {
        "mainInformation": {
            "brand": {
                "name": "Nivea",
                "slug": "nivea",
                "imagePath": "https://www-leshop-ch-cld-res.cloudinary.com/image/upload/{stack}/v1656506258/brands/Nivea_Beiersdorf_AG_Logo"
            },
            "rating": {
                "nbReviews": 1,
                "nbStars": 5.0
            },
            "migipediaUrl": "https://migipedia.migros.ch/de/products/514672400000"
        },
        "otherInformation": {
            "articleNumber": "514672400000",
            "distributorName": "Migros-Genossenschafts-Bund",
            "distributorStreetAndNumber": "Limmatstrasse 152, CH-8031 Zürich",
            "mainSpecificities": [
                {
                    "code": "Product type",
                    "value": "Shampoo"
                },
                {
                    "code": "Requirements/uses",
                    "value": "Ausgeglichene Kopfhaut"
                },
                {
                    "code": "Suitable for",
                    "value": "Schuppige / empfindliche Kopfhaut"
                }
            ]
        }
    },
    "gtins": [
        "4005900909428"
    ],
    "images": [
        {
            "cdn": "rokka",
            "url": "https://image.migros.ch/d/{stack}/o-af-1-t.clr-fff/3bd20150bcfa6b62947eac9036738aa906cdfe1a/nivea-men-sensitive-posh.jpg"
        }
    ],
    "breadcrumb": [
        {
            "id": "7494743",
            "name": "Drugstore & cosmetics",
            "slugs": [
                "drugstore-cosmetics"
            ]
        },
        {
            "id": "7494825",
            "name": "Hair care",
            "slugs": [
                "drugstore-cosmetics",
                "hair-care"
            ]
        },
        {
            "id": "7495232",
            "name": "Shampoos",
            "slugs": [
                "drugstore-cosmetics",
                "hair-care",
                "shampoos"
            ]
        }
    ],
    "productUrls": "https://www.migros.ch/en/product/514672400000",
    "isMgbCompatible": true,
    "isConsignmentProduct": false,
    "offer": {
        "price": {
            "displayUnitPrice": true,
            "formattedPrice": "3.60",
            "advertisedDisplayValue": "3.60",
            "effectiveDisplayValue": "3.60",
            "multiplier": 1,
            "value": 3.6,
            "effectiveValue": 3.6,
            "advertisedValue": 3.6,
            "unitPrice": {
                "value": 1.44,
                "unit": "100ml"
            }
        },
        "quantity": "250ml",
        "quantityPrice": "1.44/100ml",
        "isVariableWeight": false,
        "channel": {
            "offerType": "OFFLINE",
            "region": "national"
        },
        "maxOrderableQuantityV2": 96,
        "isNewOffer": false,
        "displayPrice": true,
        "type": "STANDARD"
    },
    "dateAdded": "2024-09-16T21:23:43"
}