{
    "uid": 100053569,
    "migrosId": "514830400000",
    "name": "Garnier Belle Color 20 Hellbraun",
    "brand": "Belle Color",
    "title": "Garnier Belle Color 20 Hellbraun",
    "productRange": "STANDARD",
    "productAvailability": "INSTORE_ONLY",
    "productInformation": {
        "mainInformation": {
            "brand": {
                "name": "Belle Color",
                "slug": "belle-color"
            },
            "rating": {
                "nbReviews": 5,
                "nbStars": 4.5
            },
            "migipediaUrl": "https://migipedia.migros.ch/de/products/514830400000"
        },
        "otherInformation": {
            "articleNumber": "514830400000",
            "distributorName": "Migros-Genossenschafts-Bund",
            "distributorStreetAndNumber": "Limmatstrasse 152, CH-8031 Zürich",
            "mainSpecificities": [
                {
                    "code": "Dye",
                    "value": "braun"
                },
                {
                    "code": "Application",
                    "value": "Färben"
                }
            ]
        }
    },
    "gtins": [
        "9006100076472"
    ],
    "images": [
        {
            "cdn": "rokka",
            "url": "https://image.migros.ch/d/{stack}/o-af-1-t.clr-fff/e836a4dbf8e66233e44a255d17c2b2ead47e9d64/garnier-belle-color-20-hellbraun.jpg"
        }
    ],
    "breadcrumb": [
        {
            "id": "7494743",
            "name": "Drugstore & cosmetics",
            "slugs": [
                "drugstore-cosmetics"
            ]
        },
        {
            "id": "7494825",
            "name": "Hair care",
            "slugs": [
                "drugstore-cosmetics",
                "hair-care"
            ]
        },
        {
            "id": "7495236",
            "name": "Hair dyes",
            "slugs": [
                "drugstore-cosmetics",
                "hair-care",
                "hair-dyes"
            ]
        }
    ],
    "productUrls": "https://www.migros.ch/en/product/514830400000",
    "isMgbCompatible": true,
    "isConsignmentProduct": false,
    "offer": {
        "price": {
            "displayUnitPrice": false,
            "formattedPrice": "6.45",
            "advertisedDisplayValue": "6.45",
            "effectiveDisplayValue": "6.45",
            "multiplier": 1,
            "value": 6.45,
            "effectiveValue": 6.45,
            "advertisedValue": 6.45
        },
        "promotionPrice": {
            "displayUnitPrice": true,
            "formattedPrice": "4.55",
            "advertisedDisplayValue": "4.55",
            "effectiveDisplayValue": "4.55",
            "multiplier": 1,
            "value": 4.55,
            "effectiveValue": 4.55,
            "advertisedValue": 4.55,
            "unitPrice": {
                "value": 4.55,
                "unit": "piece"
            }
        },
        "priceInsteadOfLabel": "was",
        "quantity": "1 Stk.",
        "quantityPrice": "4.55/piece",
        "isVariableWeight": false,
        "channel": {
            "offerType": "OFFLINE",
            "region": "national"
        },
        "maxOrderableQuantityV2": 96,
        "badges": [
            {
                "type": "PERCENTAGE_PROMOTION",
                "description": "30%"
            },
            {
                "type": "MINIMUM_PIECES",
                "description": "2 or more"
            }
        ],
        "promotionDateRange": {
            "startDate": "2024-09-17",
            "endDate": "2024-09-30"
        },
        "isNewOffer": false,
        "displayPrice": true,
        "type": "STANDARD"
    },
    "dateAdded": "2024-09-17T07:23:54"
}