{
    "uid": 100079104,
    "migrosId": "517642100000",
    "name": "MNY SSTAY INK CRAYON 10",
    "brand": "Maybelline",
    "title": "MNY SSTAY INK CRAYON 10",
    "productRange": "STANDARD",
    "productAvailability": "INSTORE_ONLY",
    "productInformation": {
        "mainInformation": {
            "brand": {
                "name": "Maybelline",
                "slug": "maybelline",
                "imagePath": "https://www-leshop-ch-cld-res.cloudinary.com/image/upload/{stack}/v1640076963/brands/Maybelline_L_Ore%DD%81al_Suisse_SA_Logo"
            },
            "rating": {
                "nbReviews": 1,
                "nbStars": 5.0
            },
            "migipediaUrl": "https://migipedia.migros.ch/de/products/517642100000"
        },
        "otherInformation": {
            "articleNumber": "517642100000",
            "distributorName": "Migros-Genossenschafts-Bund",
            "distributorStreetAndNumber": "Limmatstrasse 152, CH-8031 Zürich"
        }
    },
    "gtins": [
        "30174177"
    ],
    "images": [
        {
            "cdn": "rokka",
            "url": "https://image.migros.ch/d/{stack}/o-af-1-t.clr-fff/abd665dd3112420ef997ee9a650a96ea0086ccaa/mny-sstay-ink-crayon-10.jpg"
        },
        {
            "cdn": "rokka",
            "url": "https://image.migros.ch/d/{stack}/28f27f43779e21072e43aada7f28a7d1bf30ca93.jpg"
        },
        {
            "cdn": "rokka",
            "url": "https://image.migros.ch/d/{stack}/3607a458e4c8fdcad28247d81515c412999c5443.jpg"
        },
        {
            "cdn": "rokka",
            "url": "https://image.migros.ch/d/{stack}/84ecda503531923d1d8983227b6f365458fcc348.jpg"
        }
    ],
    "breadcrumb": [
        {
            "id": "7494743",
            "name": "Drugstore & cosmetics",
            "slugs": [
                "drugstore-cosmetics"
            ]
        },
        {
            "id": "7494828",
            "name": "Facial care",
            "slugs": [
                "drugstore-cosmetics",
                "facial-care"
            ]
        },
        {
            "id": "7495247",
            "name": "Make-up",
            "slugs": [
                "drugstore-cosmetics",
                "facial-care",
                "make-up"
            ]
        }
    ],
    "productUrls": "https://www.migros.ch/en/product/517642100000",
    "isMgbCompatible": true,
    "isConsignmentProduct": false,
    "offer": {
        "price": {
            "displayUnitPrice": false,
            "formattedPrice": "13.40",
            "advertisedDisplayValue": "13.40",
            "effectiveDisplayValue": "13.40",
            "multiplier": 1,
            "value": 13.4,
            "effectiveValue": 13.4,
            "advertisedValue": 13.4
        },
        "isVariableWeight": false,
        "channel": {
            "offerType": "OFFLINE",
            "region": "national"
        },
        "maxOrderableQuantityV2": 96,
        "isNewOffer": false,
        "displayPrice": true,
        "type": "STANDARD"
    },
    "dateAdded": "2024-09-16T20:19:28"
}