{
    "uid": 100067510,
    "migrosId": "519629500000",
    "name": "Infaillible Brows 24h Filling Trangular eyebrow pencil 8.0 Light Cool Blonde",
    "brand": "L'Oréal Paris",
    "title": "Infaillible Brows 24h Filling Trangular eyebrow pencil 8.0 Light Cool Blonde",
    "productRange": "STANDARD",
    "productAvailability": "INSTORE_ONLY",
    "productInformation": {
        "mainInformation": {
            "brand": {
                "name": "L'Oréal Paris",
                "slug": "loreal-paris",
                "imagePath": "https://www-leshop-ch-cld-res.cloudinary.com/image/upload/{stack}/v1640076902/brands/Loreal_Paris_L_Ore%DD%81al_Suisse_SA_Logo"
            },
            "migipediaUrl": "https://migipedia.migros.ch/de/products/519629500000"
        },
        "otherInformation": {
            "articleNumber": "519629500000",
            "distributorName": "Migros-Genossenschafts-Bund",
            "distributorStreetAndNumber": "Limmatstrasse 152, CH-8031 Zürich"
        }
    },
    "gtins": [
        "3600524054595",
        "3600523352869"
    ],
    "images": [
        {
            "cdn": "rokka",
            "url": "https://image.migros.ch/d/{stack}/o-af-1-t.clr-fff/e3b05cbadabc8b00f749994de56e585954d81b01/infaillible-brows-24h-filling-trangular-eyebrow-pencil-80-li.jpg"
        }
    ],
    "breadcrumb": [
        {
            "id": "7494743",
            "name": "Drugstore & cosmetics",
            "slugs": [
                "drugstore-cosmetics"
            ]
        },
        {
            "id": "7494828",
            "name": "Facial care",
            "slugs": [
                "drugstore-cosmetics",
                "facial-care"
            ]
        },
        {
            "id": "7495247",
            "name": "Make-up",
            "slugs": [
                "drugstore-cosmetics",
                "facial-care",
                "make-up"
            ]
        }
    ],
    "productUrls": "https://www.migros.ch/en/product/519629500000",
    "isMgbCompatible": true,
    "isConsignmentProduct": false,
    "offer": {
        "price": {
            "displayUnitPrice": false,
            "formattedPrice": "14.95",
            "advertisedDisplayValue": "14.95",
            "effectiveDisplayValue": "14.95",
            "multiplier": 1,
            "value": 14.95,
            "effectiveValue": 14.95,
            "advertisedValue": 14.95
        },
        "isVariableWeight": false,
        "channel": {
            "offerType": "OFFLINE",
            "region": "national"
        },
        "maxOrderableQuantityV2": 96,
        "isNewOffer": false,
        "displayPrice": true,
        "type": "STANDARD"
    },
    "dateAdded": "2024-09-16T22:37:04"
}