{
    "uid": 100017877,
    "migrosId": "706047200000",
    "migrosOnlineId": "5866175",
    "name": "Microfibre replacement mop",
    "brand": "Miobrill",
    "brandLine": "Combi-system",
    "title": "Miobrill Combi-system · Microfibre replacement mop",
    "description": "Miobrill Microfibre replacement mop ",
    "productRange": "STANDARD",
    "productAvailability": "ONLINE_AND_INSTORE",
    "productInformation": {
        "mainInformation": {
            "brand": {
                "name": "Miobrill",
                "slug": "miobrill",
                "imagePath": "https://www-leshop-ch-cld-res.cloudinary.com/image/upload/{stack}/v1661928614/brands/Miobrill"
            },
            "mcheck": {
                "carbonFootprint": {
                    "rating": 1,
                    "co2CarKmEquivalent": 188,
                    "productionRatio": 99,
                    "transportRatio": 0,
                    "packagingRatio": 1,
                    "image": "https://image.migros.ch/original/3e5cee492451bdf61aaed46537f4e5c8eb9a9b98.svg",
                    "stackImage": "https://image.migros.ch/{stack}/3e5cee492451bdf61aaed46537f4e5c8eb9a9b98.svg",
                    "co2KgRange": "≥10 kg CO₂eq / kg"
                }
            },
            "rating": {
                "nbReviews": 29,
                "nbStars": 3.0
            },
            "migipediaUrl": "https://migipedia.migros.ch/de/products/706047200000"
        },
        "otherInformation": {
            "articleNumber": "706047200000",
            "distributorName": "Migros-Genossenschafts-Bund",
            "distributorStreetAndNumber": "Limmatstrasse 152, CH-8031 Zürich",
            "mainSpecificities": [
                {
                    "code": "Area of application",
                    "value": "feucht, nass"
                },
                {
                    "code": "Number",
                    "value": "1 Pcs."
                },
                {
                    "code": "Material",
                    "value": "Polyester"
                },
                {
                    "code": "Washing instructions",
                    "value": "Do not tumble dry, Bleaching not permitted, Non-chemical cleaning, Do not iron, 60°"
                },
                {
                    "code": "Color",
                    "value": "grau"
                },
                {
                    "code": "Note",
                    "value": "Keinen Weichspüler verwenden, Mit ähnlichen Farben waschen, kann abfärben"
                }
            ]
        }
    },
    "gtins": [
        "7613432305204"
    ],
    "images": [
        {
            "cdn": "rokka",
            "url": "https://image.migros.ch/{stack}/be083f5275a3c505c7238d4750b6479756c1f1e5/microfaser-ersatzmop.jpg"
        }
    ],
    "breadcrumb": [
        {
            "id": "7494740",
            "name": "Laundry & cleaning",
            "slugs": [
                "laundry-cleaning"
            ]
        },
        {
            "id": "7494810",
            "name": "Cleaning utensils",
            "slugs": [
                "laundry-cleaning",
                "cleaning-utensils"
            ]
        },
        {
            "id": "7495156",
            "name": "Buckets, floor wipes & brooms",
            "slugs": [
                "laundry-cleaning",
                "cleaning-utensils",
                "buckets-floor-wipes-brooms"
            ]
        }
    ],
    "productUrls": "https://www.migros.ch/en/product/706047200000",
    "isMgbCompatible": true,
    "isConsignmentProduct": false,
    "offer": {
        "price": {
            "displayUnitPrice": true,
            "formattedPrice": "14.95",
            "advertisedDisplayValue": "14.95",
            "effectiveDisplayValue": "14.95",
            "multiplier": 1,
            "value": 14.95,
            "effectiveValue": 14.95,
            "advertisedValue": 14.95,
            "unitPrice": {
                "value": 14.95,
                "unit": "piece"
            }
        },
        "quantity": "1 Stk.",
        "quantityPrice": "14.95/piece",
        "isVariableWeight": false,
        "channel": {
            "offerType": "OFFLINE",
            "region": "national"
        },
        "maxOrderableQuantityV2": 96,
        "isNewOffer": false,
        "displayPrice": true,
        "type": "STANDARD"
    },
    "dateAdded": "2024-09-16T08:35:30"
}