{
    "uid": 100017840,
    "migrosId": "706606300000",
    "migrosOnlineId": "5866099",
    "name": "Household gloves extra long",
    "brand": "Miobrill",
    "versioning": "Size M",
    "title": "Miobrill · Household gloves extra long · Size M",
    "description": "Miobrill Household gloves extra long Size M Thin cotton flock lining",
    "productRange": "STANDARD",
    "productAvailability": "ONLINE_AND_INSTORE",
    "productInformation": {
        "mainInformation": {
            "labels": [
                {
                    "id": "L09",
                    "name": "FSC®",
                    "slug": "fsc",
                    "imagePath": "https://www-leshop-ch-cld-res.cloudinary.com/image/upload/{stack}/v1679483057/labels/FSC_-_RGB_-_DE"
                }
            ],
            "brand": {
                "name": "Miobrill",
                "slug": "miobrill",
                "imagePath": "https://www-leshop-ch-cld-res.cloudinary.com/image/upload/{stack}/v1661928614/brands/Miobrill"
            },
            "mcheck": {
                "carbonFootprint": {
                    "rating": 1,
                    "co2CarKmEquivalent": 188,
                    "productionRatio": 99,
                    "transportRatio": 0,
                    "packagingRatio": 1,
                    "image": "https://image.migros.ch/original/3e5cee492451bdf61aaed46537f4e5c8eb9a9b98.svg",
                    "stackImage": "https://image.migros.ch/{stack}/3e5cee492451bdf61aaed46537f4e5c8eb9a9b98.svg",
                    "co2KgRange": "≥10 kg CO₂eq / kg"
                }
            },
            "rating": {
                "nbReviews": 26,
                "nbStars": 4.5
            },
            "migipediaUrl": "https://migipedia.migros.ch/de/products/706606300000"
        },
        "usageInformation": {
            "additionalInformation": "Made of latex with cotton flock lining. Better protection of the arms thanks to long cuff. No water seepage."
        },
        "otherInformation": {
            "articleNumber": "706606300000",
            "distributorName": "Migros-Genossenschafts-Bund",
            "distributorStreetAndNumber": "Limmatstrasse 152, CH-8031 Zürich",
            "mainSpecificities": [
                {
                    "code": "Number",
                    "value": "1 Pair"
                },
                {
                    "code": "Dimensions/size",
                    "value": "M"
                },
                {
                    "code": "Material",
                    "value": "Baumwolle, Latex"
                },
                {
                    "code": "Color",
                    "value": "gelb"
                },
                {
                    "code": "Note",
                    "value": "nicht beständig gegen Öle, Fette, Laugen und Verdünner"
                }
            ]
        }
    },
    "gtins": [
        "7613347432576"
    ],
    "images": [
        {
            "cdn": "rokka",
            "url": "https://image.migros.ch/{stack}/2e0e776f8934d99e9e1ebbc1e4e74184f60a9563/gloves-extra-lon.jpg"
        }
    ],
    "breadcrumb": [
        {
            "id": "7494740",
            "name": "Laundry & cleaning",
            "slugs": [
                "laundry-cleaning"
            ]
        },
        {
            "id": "7494810",
            "name": "Cleaning utensils",
            "slugs": [
                "laundry-cleaning",
                "cleaning-utensils"
            ]
        },
        {
            "id": "7495158",
            "name": "Gloves, sponges & brushes",
            "slugs": [
                "laundry-cleaning",
                "cleaning-utensils",
                "gloves-sponges-brushes"
            ]
        }
    ],
    "productUrls": "https://www.migros.ch/en/product/706606300000",
    "isMgbCompatible": true,
    "isConsignmentProduct": false,
    "offer": {
        "price": {
            "displayUnitPrice": true,
            "formattedPrice": "1.95",
            "advertisedDisplayValue": "1.95",
            "effectiveDisplayValue": "1.95",
            "multiplier": 1,
            "value": 1.95,
            "effectiveValue": 1.95,
            "advertisedValue": 1.95,
            "unitPrice": {
                "value": 1.95,
                "unit": "piece"
            }
        },
        "quantity": "1 Stk.",
        "quantityPrice": "1.95/piece",
        "isVariableWeight": false,
        "channel": {
            "offerType": "OFFLINE",
            "region": "national"
        },
        "maxOrderableQuantityV2": 96,
        "isNewOffer": false,
        "displayPrice": true,
        "type": "STANDARD"
    },
    "dateAdded": "2024-09-16T08:52:31"
}