{
    "uid": 100165118,
    "migrosId": "711127600000",
    "name": "Confetti shooter",
    "brand": "MIGROS HOME",
    "title": "Confetti shooter",
    "productRange": "STANDARD",
    "productAvailability": "INSTORE_ONLY",
    "productInformation": {
        "mainInformation": {
            "brand": {
                "name": "MIGROS HOME",
                "slug": "migros-home",
                "imagePath": "https://www-leshop-ch-cld-res.cloudinary.com/image/upload/{stack}/v1715075047/brands/MIGROS_Home_GR7"
            },
            "origin": "You can find information about the origin on the packaging in the store.",
            "migipediaUrl": "https://migipedia.migros.ch/de/products/711127600000"
        },
        "otherInformation": {
            "articleNumber": "711127600000",
            "distributorName": "Migros-Genossenschafts-Bund",
            "distributorStreetAndNumber": "Limmatstrasse 152, CH-8031 Zürich"
        }
    },
    "gtins": [
        "7628871069228"
    ],
    "images": [
        {
            "cdn": "rokka",
            "url": "https://image.migros.ch/{stack}/9b1a2322ea6661a946353d874fb57e5e88e64946/confetti-shooter.jpg"
        }
    ],
    "breadcrumb": [
        {
            "id": "7494741",
            "name": "Household and living",
            "slugs": [
                "household-and-living"
            ]
        },
        {
            "id": "7494813",
            "name": "Office & stationery",
            "slugs": [
                "household-and-living",
                "office-stationery"
            ]
        },
        {
            "id": "7495173",
            "name": "Party & decoration",
            "slugs": [
                "household-and-living",
                "office-stationery",
                "party-decoration"
            ]
        }
    ],
    "productUrls": "https://www.migros.ch/en/product/711127600000",
    "isMgbCompatible": true,
    "isConsignmentProduct": false,
    "offer": {
        "price": {
            "displayUnitPrice": false,
            "formattedPrice": "5.95",
            "advertisedDisplayValue": "5.95",
            "effectiveDisplayValue": "5.95",
            "multiplier": 1,
            "value": 5.95,
            "effectiveValue": 5.95,
            "advertisedValue": 5.95
        },
        "quantity": "1 Stk.",
        "isVariableWeight": false,
        "channel": {
            "offerType": "OFFLINE",
            "region": "national"
        },
        "maxOrderableQuantityV2": 96,
        "isNewOffer": false,
        "displayPrice": true,
        "type": "STANDARD"
    },
    "dateAdded": "2024-09-17T08:22:21"
}